pytoexe/Example.py
pytoexe/ExampleScript.py
pytoexe/__init__.py
pytoexe/__main__.py
pytoexe/main.py
pytoexe-1.0.7.dist-info/METADATA
pytoexe-1.0.7.dist-info/WHEEL
pytoexe-1.0.7.dist-info/top_level.txt
pytoexe-1.0.7.dist-info/RECORD
