Metadata-Version: 1.2
Name: pytoexe
Version: 1.0.7
Summary: A Python module to convert python scripts to exe
Home-page: UNKNOWN
Author: pennacap
Maintainer: pennacap
License: UNKNOWN
Platform: UNKNOWN
Requires: cx_Freeze
Requires-Python: >=3.5.2
